segmoe/__init__.py
segmoe/cli.py
segmoe/main.py
segmoe-0.0.4.dist-info/METADATA
segmoe-0.0.4.dist-info/WHEEL
segmoe-0.0.4.dist-info/entry_points.txt
segmoe-0.0.4.dist-info/top_level.txt
segmoe-0.0.4.dist-info/RECORD
