Metadata-Version: 2.1
Name: segmoe
Version: 0.0.4
Summary: Package for Mixing Stable Diffusiion XL Models by Segmind
Home-page: https://github.com/segmind/segmoe
Author: Yatharth Gupta
Author-email: yatharthg@segmind.com
License: MIT
Platform: UNKNOWN
Requires-Dist: accelerate
Requires-Dist: diffusers
Requires-Dist: safetensors
Requires-Dist: torch (>=2.0.0)
Requires-Dist: transformers
